vcfsynonymous/__init__.py
vcfsynonymous/__main__.py
vcfsynonymous/arguments.py
vcfsynonymous/dbfasta2CdsSeq.py
vcfsynonymous/objets.py
vcfsynonymous/synonymous.py
vcfsynonymous-0.2.0.dist-info/LICENSE
vcfsynonymous-0.2.0.dist-info/METADATA
vcfsynonymous-0.2.0.dist-info/WHEEL
vcfsynonymous-0.2.0.dist-info/entry_points.txt
vcfsynonymous-0.2.0.dist-info/top_level.txt
vcfsynonymous-0.2.0.dist-info/RECORD
