Metadata-Version: 2.1
Name: vcfsynonymous
Version: 0.2.0
Summary: Detect synonymous genetic variants in VCF
Home-page: https://github.com/Grelot/vcfsynonymous
Author: Pierre-Edouard GUERIN
Author-email: pierre-edouard.guerin@cefe.cnrs.fr
License: MIT
Platform: UNKNOWN
Classifier: Programming Language :: Python :: 3
Classifier: Programming Language :: Python :: 3.6
Classifier: Programming Language :: Python :: 3.7
Classifier: Programming Language :: Python :: 3.8
Classifier: License :: OSI Approved :: MIT License
Classifier: Operating System :: OS Independent
Requires-Dist: argparse
Requires-Dist: numpy
Requires-Dist: biopython
Requires-Dist: bcbio-gff
Requires-Dist: pyfaidx
Requires-Dist: gffutils
Requires-Dist: PyVCF
